makkulupy/__init__.py
makkulupy/exceptions.py
makkulupy/requests.py
makkulupy/models/__init__.py
makkulupy/models/batch.py
makkulupy/models/word.py
makkulupy/tests/__init__.py
makkulupy/tests/test_requests.py
makkulupy-0.3.1.dist-info/LICENSE
makkulupy-0.3.1.dist-info/WHEEL
makkulupy-0.3.1.dist-info/METADATA
makkulupy-0.3.1.dist-info/RECORD
